sqladaptor/__init__.py
sqladaptor/sqlite.py
sqladaptor-0.5.0.dist-info/METADATA
sqladaptor-0.5.0.dist-info/WHEEL
sqladaptor-0.5.0.dist-info/licenses/LICENSE
sqladaptor-0.5.0.dist-info/RECORD
