Metadata-Version: 2.3
Name: sqladaptor
Version: 0.5.0
Summary: Starting adaptor for JSON/Pandas to SQL db
Project-URL: repository, https://github.com/boscoh/sqladaptor
Author-email: Bosco Ho <apposite@gmail.com>
License-File: LICENSE
Requires-Python: >=3.8
Requires-Dist: fastjsonschema>=2.19.1
Requires-Dist: pandas>=2.2.2
Requires-Dist: path>=16.14.0
Requires-Dist: pydash>=8.0.1
Requires-Dist: pytest>=8.2.1
Requires-Dist: rich>=13.7.1
Requires-Dist: ruff-lsp>=0.0.53
Requires-Dist: ruff>=0.4.5
